nonebot_plugin_playercheck/__init__.py
nonebot_plugin_playercheck/datasource.py
nonebot_plugin_playercheck/templates/main.html
nonebot_plugin_playercheck-1.5.9.dist-info/LICENSE
nonebot_plugin_playercheck-1.5.9.dist-info/METADATA
nonebot_plugin_playercheck-1.5.9.dist-info/WHEEL
nonebot_plugin_playercheck-1.5.9.dist-info/RECORD
