Metadata-Version: 2.1
Name: nonebot-plugin-playercheck
Version: 1.5.9
Summary: 基于 Nonebot2 的群友音游成分查询
Home-page: https://github.com/Ohdmire/nonebot-plugin-playercheck
License: MIT
Author: Ohdmire
Requires-Python: >=3.8,<4
Classifier: License :: OSI Approved :: MIT License
Classifier: Programming Language :: Python :: 3
Classifier: Programming Language :: Python :: 3.8
Classifier: Programming Language :: Python :: 3.9
Classifier: Programming Language :: Python :: 3.10
Classifier: Programming Language :: Python :: 3.11
Requires-Dist: nonebot-adapter-onebot (>=2.2.3)
Requires-Dist: nonebot-plugin-htmlrender (>=0.2.1)
Requires-Dist: nonebot2 (>=2.0.0-beta.1)
Project-URL: Repository, https://github.com/Ohdmire/nonebot-plugin-playercheck
